odoo/addons/stock_release_channel_plan_process_end_time/README.rst
odoo/addons/stock_release_channel_plan_process_end_time/__init__.py
odoo/addons/stock_release_channel_plan_process_end_time/__manifest__.py
odoo/addons/stock_release_channel_plan_process_end_time/demo/stock_release_channel.xml
odoo/addons/stock_release_channel_plan_process_end_time/i18n/fr.po
odoo/addons/stock_release_channel_plan_process_end_time/i18n/it.po
odoo/addons/stock_release_channel_plan_process_end_time/i18n/stock_release_channel_plan_process_end_time.pot
odoo/addons/stock_release_channel_plan_process_end_time/readme/CONTRIBUTORS.md
odoo/addons/stock_release_channel_plan_process_end_time/readme/CREDITS.md
odoo/addons/stock_release_channel_plan_process_end_time/readme/DESCRIPTION.md
odoo/addons/stock_release_channel_plan_process_end_time/static/description/icon.png
odoo/addons/stock_release_channel_plan_process_end_time/static/description/index.html
odoo/addons/stock_release_channel_plan_process_end_time/tests/__init__.py
odoo/addons/stock_release_channel_plan_process_end_time/tests/test_stock_release_channel_plan.py
odoo/addons/stock_release_channel_plan_process_end_time/wizards/__init__.py
odoo/addons/stock_release_channel_plan_process_end_time/wizards/launch_plan.py
odoo/addons/stock_release_channel_plan_process_end_time/wizards/launch_plan.xml
odoo_addon_stock_release_channel_plan_process_end_time-18.0.1.0.0.2.dist-info/METADATA
odoo_addon_stock_release_channel_plan_process_end_time-18.0.1.0.0.2.dist-info/WHEEL
odoo_addon_stock_release_channel_plan_process_end_time-18.0.1.0.0.2.dist-info/top_level.txt
odoo_addon_stock_release_channel_plan_process_end_time-18.0.1.0.0.2.dist-info/RECORD
