Metadata-Version: 2.1
Name: odoo-addon-stock_release_channel_plan_process_end_time
Version: 18.0.1.0.0.2
Requires-Python: >=3.10
Requires-Dist: odoo-addon-stock_release_channel_plan==18.0.*
Requires-Dist: odoo-addon-stock_release_channel_process_end_time==18.0.*
Requires-Dist: odoo==18.0.*
Summary: Glue module between release channel plan and process end time
Home-page: https://github.com/OCA/stock-logistics-release-channel
License: AGPL-3
Author: BCIM,Odoo Community Association (OCA)
Author-email: support@odoo-community.org
Classifier: Programming Language :: Python
Classifier: Framework :: Odoo
Classifier: Framework :: Odoo :: 18.0
Classifier: License :: OSI Approved :: GNU Affero General Public License v3
Classifier: Development Status :: 4 - Beta
